FFregister.sv
module FFregisterff (input wire a, clk, res, output reg qout);
    always @(posedge clk or posedge res) begin
        if (res == 1'b1)
            qout<=1'b0;
        else 
            qout <=a;
    end
endmodule

module FFregister (input a, clk, res, output reg qout, output reg [7:0] outbit);
    wire [6:0] qin;
    //series out after 8 clock cycles
    FFregisterff bit1 (.a(a), .clk(clk), .res(res), .qout(qin[0]));
    FFregisterff bit2 (.a(qin[0]), .clk(clk), .res(res), .qout(qin[1]));
    FFregisterff bit3 (.a(qin[1]), .clk(clk), .res(res), .qout(qin[2]));
    FFregisterff bit4 (.a(qin[2]), .clk(clk), .res(res), .qout(qin[3]));
    FFregisterff bit5 (.a(qin[3]), .clk(clk), .res(res), .qout(qin[4]));
    FFregisterff bit6 (.a(qin[4]), .clk(clk), .res(res), .qout(qin[5]));
    FFregisterff bit7 (.a(qin[5]), .clk(clk), .res(res), .qout(qin[6]));
    FFregisterff bit8 (.a(qin[6]), .clk(clk), .res(res), .qout(qout));
    //parallel out
    always @(qout) begin
        outbit[0] = qin[0];
        outbit[1] = qin[1];
        outbit[2] = qin[2];
        outbit[3] = qin[3];
        outbit[4] = qin[4];
        outbit[5] = qin[5];
        outbit[6] = qin[6];
        outbit[7] = qout;
    end
endmodule

FFregister.vcd
$version Generated by VerilatedVcd $end
$date Thu Sep 15 16:10:01 2022 $end
$timescale 1ps $end

 $scope module TOP $end
  $var wire  1 2 a $end
  $var wire  1 3 clk $end
  $var wire  8 6 outbit [7:0] $end
  $var wire  1 5 qout $end
  $var wire  1 4 res $end
  $scope module FFregister $end
   $var wire  1 2 a $end
   $var wire  1 3 clk $end
   $var wire  8 6 outbit [7:0] $end
   $var wire  7 # qin [6:0] $end
   $var wire  1 5 qout $end
   $var wire  1 4 res $end
   $scope module bit1 $end
    $var wire  1 2 a $end
    $var wire  1 3 clk $end
    $var wire  1 $ qout $end
    $var wire  1 4 res $end
   $upscope $end
   $scope module bit2 $end
    $var wire  1 % a $end
    $var wire  1 3 clk $end
    $var wire  1 & qout $end
    $var wire  1 4 res $end
   $upscope $end
   $scope module bit3 $end
    $var wire  1 ' a $end
    $var wire  1 3 clk $end
    $var wire  1 ( qout $end
    $var wire  1 4 res $end
   $upscope $end
   $scope module bit4 $end
    $var wire  1 ) a $end
    $var wire  1 3 clk $end
    $var wire  1 * qout $end
    $var wire  1 4 res $end
   $upscope $end
   $scope module bit5 $end
    $var wire  1 + a $end
    $var wire  1 3 clk $end
    $var wire  1 , qout $end
    $var wire  1 4 res $end
   $upscope $end
   $scope module bit6 $end
    $var wire  1 - a $end
    $var wire  1 3 clk $end
    $var wire  1 . qout $end
    $var wire  1 4 res $end
   $upscope $end
   $scope module bit7 $end
    $var wire  1 / a $end
    $var wire  1 3 clk $end
    $var wire  1 0 qout $end
    $var wire  1 4 res $end
   $upscope $end
   $scope module bit8 $end
    $var wire  1 1 a $end
    $var wire  1 3 clk $end
    $var wire  1 5 qout $end
    $var wire  1 4 res $end
   $upscope $end
  $upscope $end
 $upscope $end
$enddefinitions $end


#0
b0000000 #
0$
0%
0&
0'
0(
0)
0*
0+
0,
0-
0.
0/
00
01
02
03
04
05
b00000000 6
#1
b0000001 #
1$
1%
12
13
b00000001 6
#2
02
03
#3
b0000010 #
0$
0%
1&
1'
13
b00000010 6
#4
03
#5
b0000100 #
0&
0'
1(
1)
13
b00000100 6
#6
03
#7
b0001000 #
0(
0)
1*
1+
13
b00001000 6
#8
03
#9
b0010000 #
0*
0+
1,
1-
13
b00010000 6
#10
03
#11
b0100000 #
0,
0-
1.
1/
13
b00100000 6
#12
b0000000 #
0.
0/
03
14
b00000000 6
#13
13
#14
03
#15
13
#16
03
#17
b0000001 #
1$
1%
12
13
04
b00000001 6
#18
02
03
#19
b0000010 #
0$
0%
1&
1'
13
b00000010 6
#20
03
#21
b0000100 #
0&
0'
1(
1)
13
b00000100 6
#22
03
#23
b0001000 #
0(
0)
1*
1+
13
b00001000 6
#24
03
#25
b0010000 #
0*
0+
1,
1-
13
b00010000 6
#26
03
#27
b0100000 #
0,
0-
1.
1/
13
b00100000 6
#28
03
#29
b1000000 #
0.
0/
10
11
13
b01000000 6
#30
03
#31
b0000000 #
00
01
13
15
b10000000 6
